[{
	"options": {
		"sensor_id": "0400f5d8",
		"sensor_kind": "watty"
	},
	"ObjectContent": {
		"contentData": [{
			"unitType": "℃",
			"dataValue": "0",
			"dataName": "TempData1"
		},
		{
			"unitType": "℃",
			"dataValue": "0",
			"dataName": "TempData2"
		},
		{
			"unitType": "℃",
			"dataValue": "0",
			"dataName": "TempData3"
		},
		{
			"unitType": "℃",
			"dataValue": "0",
			"dataName": "TempData4"
		}],
		"contentType": "iaCloudData"
	},
	"objectKey": "jp.co.centurysys.nodejs_test.temperature",
	"objectType": "iaCloudObject",
	"objectDescription": "ベルトコンベアの温度"
},
{
	"options": {
		"sensor_id": "04009efc",
		"sensor_kind": "u-rd"
	},
	"ObjectContent": {
		"contentData": [{
			"unitType": "A",
			"dataValue": "0",
			"dataName": "AC_1"
		}],
		"contentType": "iaCloudData"
	},
	"objectKey": "jp.co.centurysys.nodejs_test.ac",
	"objectType": "iaCloudObject",
	"objectDescription": "モーター1の電流"
}]
